drc/__init__.py
drc/cli.py
drc/drc.py
drc/parse.py
drc/plot.py
drc/test.py
dose_response-0.0.2.dist-info/METADATA
dose_response-0.0.2.dist-info/WHEEL
dose_response-0.0.2.dist-info/entry_points.txt
dose_response-0.0.2.dist-info/top_level.txt
dose_response-0.0.2.dist-info/RECORD
