Metadata-Version: 2.1
Name: dose-response
Version: 0.0.2
Summary: Create Dose-Response-Curves from csv files
Author: Tim Hörmann
Author-email: t.hoermann@audivir.de
Project-URL: homepage, https://www.audivir.de/
Project-URL: repository, https://github.com/tim25651/DRC
Requires-Dist: matplotlib
Requires-Dist: numpy
Requires-Dist: pandas
Requires-Dist: scipy
